duckdb_extension_delta/__init__.py
duckdb_extension_delta/extensions/v1.4.3/delta.duckdb_extension
duckdb_extension_delta-1.4.3.dist-info/METADATA
duckdb_extension_delta-1.4.3.dist-info/WHEEL
duckdb_extension_delta-1.4.3.dist-info/RECORD
