Metadata-Version: 2.4
Name: duckdb_extension_delta
Version: 1.4.3
Summary: Duckdb delta extension
Project-URL: Documentation, https://github.com/santosh-d3vpl3x/duckdb_extensions#readme
Project-URL: Issues, https://github.com/santosh-d3vpl3x/duckdb_extensions/issues
Project-URL: Source, https://github.com/santosh-d3vpl3x/duckdb_extensions
Author-email: santosh <void@some.where>
License: MIT
Classifier: Development Status :: 4 - Beta
Classifier: License :: OSI Approved :: MIT License
Classifier: Programming Language :: Python
Classifier: Programming Language :: Python :: 3.9
Classifier: Programming Language :: Python :: 3.10
Classifier: Programming Language :: Python :: 3.11
Classifier: Programming Language :: Python :: 3.12
Classifier: Programming Language :: Python :: 3.13
Classifier: Programming Language :: Python :: Implementation :: CPython
Classifier: Programming Language :: Python :: Implementation :: PyPy
Requires-Python: >=3.9
Requires-Dist: duckdb==1.4.3
